hashi/__init__.py
hashi/__main__.py
hashi-0.1.0.dist-info/METADATA
hashi-0.1.0.dist-info/WHEEL
hashi-0.1.0.dist-info/entry_points.txt
hashi-0.1.0.dist-info/top_level.txt
hashi-0.1.0.dist-info/RECORD
