Metadata-Version: 2.4
Name: hashi
Version: 0.1.0
Summary: Hashiwokakero puzzle engine for generating, solving, and playing.
Author-email: Al Sweigart <al@inventwithpython.com>
Classifier: Programming Language :: Python :: 3
Classifier: Operating System :: OS Independent
Requires-Python: >=3.8
